lisaanalysistools/git_version.py
lisatools/detector.py
lisatools/datacontainer.py
lisatools/_version.py
lisatools/stochastic.py
lisatools/__init__.py
lisatools/git_version.py.in
lisatools/sensitivity.py
lisatools/diagnostic.py
lisatools/analysiscontainer.py
lisatools/cutils/Detector.cu
lisatools/cutils/__init__.py
lisatools/cutils/binding.cxx
lisatools/cutils/binding.hpp
lisatools/cutils/Detector.hpp
lisatools/sampling/utility.py
lisatools/sampling/__init__.py
lisatools/sampling/prior.py
lisatools/sampling/stopping.py
lisatools/sampling/likelihood.py
lisatools/sampling/moves/__init__.py
lisatools/sampling/moves/skymodehop.py
lisatools/utils/parallelbase.py
lisatools/utils/utility.py
lisatools/utils/constants.py
lisatools/utils/__init__.py
lisatools/utils/exceptions.py
lisatools/orbit_files/equalarmlength-orbits.h5
lisatools/orbit_files/esa-trailing-orbits.h5
lisatools/orbit_files/equalarmlength-orbits-best-fit-to-esa.h5
lisatools/.dylibs/libstdc++.6.dylib
lisatools/.dylibs/libgcc_s.1.1.dylib
lisatools/sources/waveformbase.py
lisatools/sources/__init__.py
lisatools/sources/utils.py
lisatools/sources/defaultresponse.py
lisatools/sources/gb/waveform.py
lisatools/sources/gb/__init__.py
lisatools/sources/bbh/waveform.py
lisatools/sources/bbh/__init__.py
lisatools/sources/emri/waveform.py
lisatools/sources/emri/__init__.py
lisatools_backend_cpu/pycppdetector.cpython-310-darwin.so
lisatools_backend_cpu/libdetector.a
lisatools_backend_cpu/git_version.py
lisaanalysistools-1.2.5.dist-info/RECORD
lisaanalysistools-1.2.5.dist-info/WHEEL
lisaanalysistools-1.2.5.dist-info/METADATA
lisaanalysistools-1.2.5.dist-info/licenses/LICENSE
